regressormetricgraphplot/CompareModels.py
regressormetricgraphplot/__init__.py
regressormetricgraphplot-0.0.3.dist-info/LICENSE
regressormetricgraphplot-0.0.3.dist-info/METADATA
regressormetricgraphplot-0.0.3.dist-info/WHEEL
regressormetricgraphplot-0.0.3.dist-info/top_level.txt
regressormetricgraphplot-0.0.3.dist-info/RECORD
