Metadata-Version: 2.1
Name: regressormetricgraphplot
Version: 0.0.3
Summary: A simple package for comparing different Regression Models and Plotting with their most common evaluation metrics.
Home-page: https://github.com/ajayarunachalam/RegressorMetricGraphPlot
Author: Ajay Arunachalam
Author-email: ajay.arunachalam08@gmail.com
License: MIT
Platform: UNKNOWN
